pq_ntru/NTRUdecrypt.py
pq_ntru/NTRUencrypt.py
pq_ntru/NTRUutil.py
pq_ntru/__init__.py
pq_ntru/ntru.py
pq_ntru-0.1.3.dist-info/METADATA
pq_ntru-0.1.3.dist-info/WHEEL
pq_ntru-0.1.3.dist-info/top_level.txt
pq_ntru-0.1.3.dist-info/RECORD
