Metadata-Version: 2.1
Name: pq-ntru
Version: 0.1.3
Summary: A quantum proof (post-quantum) implementation of the NTRU algorithm
Home-page: https://github.com/protdos/pq-ntru
Author: CodingLive | ProtDos
Author-email: <rootcode@duck.com>
Keywords: python,python3,post-quantum,ntru,quantum-proof,crypto,cryptography,lattice,svp,numpy,sympy
Classifier: Development Status :: 3 - Alpha
Classifier: Intended Audience :: Developers
Classifier: Programming Language :: Python :: 3
Classifier: Operating System :: Unix
Classifier: Operating System :: MacOS :: MacOS X
Classifier: Operating System :: Microsoft :: Windows
Requires-Dist: numpy
Requires-Dist: sympy
